MANIFEST.in
setup.py
aero/__init__.py
aero/app.py
aero/console.py
aero/static.py
aero/template.py
aero/version.py
aero.egg-info/PKG-INFO
aero.egg-info/SOURCES.txt
aero.egg-info/dependency_links.txt
aero.egg-info/entry_points.txt
aero.egg-info/requires.txt
aero.egg-info/top_level.txt
aero/apps/__init__.py
aero/apps/healthcheck/__init__.py
aero/apps/healthcheck/handlers.py
aero/apps/healthcheck/urls.py
aero/apps/healthcheck/templates/aero/healthcheck/working.html
vows/__init__.py
vows/aero_static_vows.py
vows/bus_vows.py
vows/tornado_app_vows.py
vows/version_vows.py
vows/console_app/__init__.py
vows/fixtures/__init__.py
vows/fixtures/apps/__init__.py
vows/fixtures/apps/staticapp/__init__.py