Metadata-Version: 1.0
Name: aero
Version: 0.3.0a
Summary: aero adds django-like apps support to tornado and automates common actions
Home-page: http://heynemann.github.com/aero/
Author: Bernardo Heynemann
Author-email: heynemann@gmail.com
License: MIT
Keywords: tornado aero app django
Platform: UNKNOWN
Classifier: Development Status :: 3 - Alpha
Classifier: Intended Audience :: Developers
Classifier: License :: OSI Approved :: MIT License
Classifier: Natural Language :: English
Classifier: Operating System :: MacOS
Classifier: Operating System :: POSIX :: Linux
Classifier: Programming Language :: Python :: 2.6
